AUTHORS
LICENSE
MANIFEST.in
README.md
setup.py
python_social_auth_waveapps.egg-info/PKG-INFO
python_social_auth_waveapps.egg-info/SOURCES.txt
python_social_auth_waveapps.egg-info/dependency_links.txt
python_social_auth_waveapps.egg-info/requires.txt
python_social_auth_waveapps.egg-info/top_level.txt
social_auth_waveapps/__init__.py
social_auth_waveapps/backends.py
social_auth_waveapps/models.py