Metadata-Version: 1.1
Name: python-social-auth-waveapps
Version: 0.1.0
Summary: Waveapps backend for python-social-auth.
Home-page: https://github.com/ashchristopher/python-social-auth-waveapps
Author: Ash Christopher
Author-email: ash.christopher@gmail.com
License: LICENSE
Keywords: django social auth oauth2 social-auth waveapps
Platform: UNKNOWN
Classifier: Development Status :: 2 - Pre-Alpha
Classifier: Framework :: Django
Classifier: Intended Audience :: Developers
Classifier: License :: OSI Approved :: MIT License
Classifier: Operating System :: OS Independent
Classifier: Topic :: Software Development
